Workbook

Sheet Private Clinic Plans
A1: Implanr — Private Clinic Subscription Plans
A2: Premium implant workflow platform. Less than the cost of one implant case per month.
A3: SOLO | C3: CLINIC | E3: SPECIALIST | G3: ENTERPRISE | I3: CHAIN / GROUP 50+ users Custom Pricing Call us
A4: Built for the solo implantologist | C4: The complete clinic workflow | E4: For high-volume implant centres | G4: Multi-branch clinic group
A5: 1-3 users | C5: 4-10 users | E5: 11-25 users | G5: 26-50 users
A6: Rs 3,500/mo | C6: Rs 6,000/mo | E6: Rs 10,000/mo | G6: Rs 18,000/mo
A7: Rs 35,000/yr (save Rs 7,000) | C7: Rs 60,000/yr (save Rs 12,000) | E7: Rs 1,00,000/yr (save Rs 20,000) | G7: Rs 1,80,000/yr (save Rs 36,000)
A8: Just Rs 117/day — less than one implant case/month | C8: Just Rs 200/day — less than one implant case/month | E8: Just Rs 333/day — less than one implant case/month | G8: Just Rs 600/day — less than one implant case/month
A10: WHAT IS INCLUDED IN EVERY PLAN
A11: Feature | B11: Solo | C11: Clinic | D11: Enterprise | E11: Enterprise
A12: iOS + Android App | B12: Yes | C12: Yes | D12: Yes | E12: Yes
A13: Implant Case Management | B13: Yes | C13: Yes | D13: Yes | E13: Yes
A14: CBCT File Upload & Viewing | B14: Yes | C14: Yes | D14: Yes | E14: Yes
A15: AI-Assisted Treatment Planning | B15: No | C15: Yes | D15: Yes | E15: Yes
A16: AI-Assisted Summery | B16: Yes | C16: Yes | D16: Yes | E16: Yes
A17: PDF Report Generation | B17: Yes | C17: Yes | D17: Yes | E17: Yes
A18: Push Notifications | B18: Yes | C18: Yes | D18: Yes | E18: Yes
A19: Patient Records & History | B19: Yes | C19: Yes | D19: Yes | E19: Yes
A20: Multi-Role Team Access | B20: Limited | C20: Yes | D20: Yes | E20: Yes
A21: Clinic Admin Dashboard | B21: No | C21: Yes | D21: Yes | E21: Yes
A22: Analytics & Case Reports | B22: Basic | C22: Standard | D22: Full | E22: Full
... A27: Onboarding & Training | B27: 1 session | C27: 3 session | D27: Full onboarding | E27: Full onboarding
A28: Max Active Cases /month | B28: 25 | C28: Unlimited | D28: Unlimited | E28: Unlimited
A30: ADD-ON USERS — Rs 500/extra user/month (Solo) | Rs 450 (Clinic) | Rs 400 (Specialist) | Rs 350 (Enterprise)

Sheet Dental College Plans
A1: Implanr — Dental College Subscription Plans (internal rate card: every college gets its own quote)
A2: One licence per implant department, Centralised Implant Clinic or Unit, sized by the PG students on its roll across all three years. Every tier has every feature; tiers differ only in size. Fellows and interns are added separately.
B3: ='College Inputs'!A6 -> Essential 9 | C3: ='College Inputs'!A7 -> Standard 12 | D3: ='College Inputs'!A8 -> Advanced 18 | E3: ='College Inputs'!A9 -> Premier 24 | F3: University / Group
A4: MDS seats per year | B4: ='College Inputs'!B6&" seats a year" -> 3 seats a year | C4: ='College Inputs'!B7&" seats a year" -> 4 seats a year | D4: ='College Inputs'!B8&" seats a year" -> 6 seats a year | E4: ='College Inputs'!B9&" seats a year" -> 8 seats a year | F4: Several colleges
A5: Licence for | B5: One department, Centralised Implant Clinic or Unit | C5: One department, Centralised Implant Clinic or Unit | D5: One department, Centralised Implant Clinic or Unit | E5: One department, Centralised Implant Clinic or Unit | F5: Every licence across member colleges
A6: PG students on roll (all 3 years) | B6: ="Up to "&'College Inputs'!D6 -> Up to 9 | C6: ="Up to "&'College Inputs'!D7 -> Up to 12 | D6: ="Up to "&'College Inputs'!D8 -> Up to 18 | E6: ="Up to "&'College Inputs'!D9&" (+ extra students)" -> Up to 24 (+ extra students) | F6: Each licence on its tier
A7: Supervisors / guides included | B7: ='College Inputs'!E6 -> 3 | C7: ='College Inputs'!E7 -> 4 | D7: ='College Inputs'!E8 -> 5 | E7: ='College Inputs'!E9 -> 6 | F7: Per licence tier
A8: Implant in-charges included | B8: ='College Inputs'!F6 -> 1 | C8: ='College Inputs'!F7 -> 2 | D8: ='College Inputs'!F8 -> 3 | E8: ='College Inputs'!F9 -> 4 | F8: Per licence tier
A9: College admins included | B9: ='College Inputs'!G6 -> 1 | C9: ='College Inputs'!G7 -> 1 | D9: ='College Inputs'!G8 -> 2 | E9: ='College Inputs'!G9 -> 2 | F9: Per licence tier + 1 group admin
A10: Annual price per licence | B10: ='College Inputs'!H6 -> 50000 | C10: ='College Inputs'!H7 -> 60000 | D10: ='College Inputs'!H8 -> 80000 | E10: ='College Inputs'!H9 -> 100000 | F10: ="Tier price less "&TEXT('College Inputs'!$B$41,"0%") -> Tier price less 15%
B11: per year + 18% GST | C11: per year + 18% GST | D11: per year + 18% GST | E11: per year + 18% GST | F11: per licence + GST
A12: Licence cost per PG per year (full tier) | B12: ='College Inputs'!H6/'College Inputs'!D6 -> 5555.5556 | C12: ='College Inputs'!H7/'College Inputs'!D7 -> 5000 | D12: ='College Inputs'!H8/'College Inputs'!D8 -> 4444.4444 | E12: ='College Inputs'!H9/'College Inputs'!D9 -> 4166.6667
A14: WHAT A WHOLE COLLEGE PAYS — examples before founding / government / 3-year discounts
A15: College set-up | B15: Licences | C15: List total | D15: Volume discount | E15: Licence fees | F15: Per PG per year
A16: 3 departments × Essential 9 | B16: 3 | C16: ='College Inputs'!$H$6+'College Inputs'!$H$6+'College Inputs'!$H$6 -> 150000 | D16: ='College Inputs'!$B$40 -> 0.15 | E16: =C16*(1-D16) -> 127500 | F16: =E16/('College Inputs'!$D$6+'College Inputs'!$D$6+'College Inputs'!$D$6) -> 4722.2222
A17: 3 departments × Standard 12 | B17: 3 | C17: ='College Inputs'!$H$7+'College Inputs'!$H$7+'College Inputs'!$H$7 -> 180000 | D17: ='College Inputs'!$B$40 -> 0.15 | E17: =C17*(1-D17) -> 153000 | F17: =E17/('College Inputs'!$D$7+'College Inputs'!$D$7+'College Inputs'!$D$7) -> 4250
A18: 3 departments × Advanced 18 | B18: 3 | C18: ='College Inputs'!$H$8+'College Inputs'!$H$8+'College Inputs'!$H$8 -> 240000 | D18: ='College Inputs'!$B$40 -> 0.15 | E18: =C18*(1-D18) -> 204000 | F18: =E18/('College Inputs'!$D$8+'College Inputs'!$D$8+'College Inputs'!$D$8) -> 3777.7778
A19: 3 departments × Premier 24 | B19: 3 | C19: ='College Inputs'!$H$9+'College Inputs'!$H$9+'College Inputs'!$H$9 -> 300000 | D19: ='College Inputs'!$B$40 -> 0.15 | E19: =C19*(1-D19) -> 255000 | F19: =E19/('College Inputs'!$D$9+'College Inputs'!$D$9+'College Inputs'!$D$9) -> 3541.6667
A20: Prostho 12 + Perio 9 + OMFS 9 | B20: 3 | C20: ='College Inputs'!$H$7+'College Inputs'!$H$6+'College Inputs'!$H$6 -> 160000 | D20: ='College Inputs'!$B$40 -> 0.15 | E20: =C20*(1-D20) -> 136000 | F20: =E20/('College Inputs'!$D$7+'College Inputs'!$D$6+'College Inputs'!$D$6) -> 4533.3333
A21: One Centralised Implant Clinic, 24 PGs | B21: 1 | C21: ='College Inputs'!$H$9 -> 100000 | D21: 0 | E21: =C21*(1-D21) -> 100000 | F21: =E21/('College Inputs'!$D$9) -> 4166.6667
A23: EXTRA USERS AND STUDENTS (per person per year + GST)
A24: Item | B24: Price | C24: When it applies
A25: Extra supervisor / guide | B25: ='College Inputs'!$B$13 -> 3000 | C25: Beyond the supervisors included across all the college's licences (allowances are pooled).
A26: Extra implant in-charge | B26: ='College Inputs'!$B$14 -> 4000 | C26: Beyond the in-charges included across all licences.
A27: Extra college admin | B27: ='College Inputs'!$B$15 -> 5000 | C27: Beyond the admins included across all licences.
A28: Extra PG student | B28: ='College Inputs'!$B$16 -> 4000 | C28: Only above 24 PGs on one Premier 24 licence (e.g. a large Centralised Implant Clinic).
A29: Fellow in Implantology | B29: ='College Inputs'!$B$17 -> 6000 | C29: Per fellow; counted separately from MDS students.
A30: Management viewer (Dean, Principal, HOD) | B30: Free | C30: Free, read-only, up to 3 per college.
A32: INTERN IMPLANT PROGRAMME — interns who place implants (observing and assisting are free)
A33: Interns per year | B33: ='College Inputs'!A22 -> Interns 20 | C33: ='College Inputs'!A23 -> Interns 40 | D33: ='College Inputs'!A24 -> Interns 60 | E33: ='College Inputs'!A25 -> Interns 80 | F33: ='College Inputs'!A26 -> Interns 100
A34: Annual price | B34: ='College Inputs'!D22 -> 15000 | C34: ='College Inputs'!D23 -> 28000 | D34: ='College Inputs'!D24 -> 40000 | E34: ='College Inputs'!D25 -> 50000 | F34: ='College Inputs'!D26 -> 60000
A35: Per intern | B35: ='College Inputs'!E22 -> 750 | C35: ='College Inputs'!E23 -> 700 | D35: ='College Inputs'!E24 -> 666.66667 | E35: ='College Inputs'!E25 -> 625 | F35: ='College Inputs'!E26 -> 600
A36: ="More than 100 interns: Interns 100 price plus "&TEXT('College Inputs'!$B$27,"#,##0")&" rupees per extra intern. Billed on the interns who will place implants that year." -> More than 100 interns: Interns 100 price plus 600 rupees per extra intern. Billed on the interns who will place implants that year.
A38: OTHER ADD-ONS
A39: Add-on | B39: Price | C39: Unit | D39: Why the college buys it
A40: Research Module | B40: ='College Inputs'!$B$32 -> 40000 | C40: per college / year | D40: Dissertation studies run inside the case records from the first enrolment.
A41: Onboarding & setup (one-time) | B41: ='College Inputs'!$B$33 -> 25000 | C41: per new college | D41: In-person launch visit and setup. Waived on 3-year contracts.
A42: Extra image storage | B42: ='College Inputs'!$B$35 -> 2500 | C42: per 100 GB / year | D42: Only above the fair-use limit per licence.
A44: WHAT EVERY LICENCE INCLUDES
A45: Feature | B45: Every licence | C45: University / Group
A46: iOS + Android app | B46: Yes | C46: Yes
A47: Implant case record — all 5 phases, unlimited cases | B47: Yes | C47: Yes
A48: CBCT upload and viewing | B48: Yes | C48: Yes
A49: AI-assisted treatment planning and case summary | B49: Yes | C49: Yes
A50: Supervisor approval gates + immutable audit trail | B50: Yes | C50: Yes
A51: PDF reports and auto lab prescription | B51: Yes | C51: Yes
A52: Lifetime maintenance recalls (Phase 5) | B52: Yes | C52: Yes
A53: Unit dashboard and analytics | B53: Yes | C53: Yes
A54: College-wide dashboard (2 or more licences) | B54: Yes | C54: Yes
A55: Consolidated multi-college dashboard | B55: — | C55: Yes
A56: Data export (CSV / PDF), any time | B56: Yes | C56: Yes
... A59: Support | B59: Email + WhatsApp | C59: Dedicated manager
A61: USER ROLES
A62: Role | B62: What they can do | E62: How counted
A63: PG student | B63: Creates and runs own cases, CBCT upload, documentation, AI notes, reports. | E63: Sets the tier (all 3 years)
A64: Fellow | B64: Same as a PG student. | E64: Per fellow, separately
A65: Intern — observe / assist | B65: Views cases; logged as assistant on supervised cases. | E65: Free
A66: Intern — places implants | B66: Own supervised cases (2–5 implants), full approval trail. | E66: Intern Programme tier
A67: Supervisor / guide | B67: Approves each phase, adds review notes, runs case reports. | E67: Included per tier; extra per user
A68: Implant in-charge | B68: Unit dashboard, enrols users, manages supervisors, academic export, audit trail. | E68: Included per tier; extra per user
A69: College admin | B69: All accounts, college-wide reports, compliance exports, college audit report. | E69: Included per tier; extra per user
A70: Management viewer | B70: Dean, Principal, HOD: read-only dashboards and reports. | E70: Free, up to 3
A72: COMMERCIAL TERMS
A73: ="Annual billing only, aligned to the start of the MDS academic session (first year pro-rated). All prices exclude GST at "&TEXT('College Inputs'!$B$48,"0%")&"." -> Annual billing only, aligned to the start of the MDS academic session (first year pro-rated). All prices exclude GST at 18%.
A74: ="Volume discount on licence fees: "&TEXT('College Inputs'!$B$39,"0%")&" for 2 licences, "&TEXT('College Inputs'!$B$40,"0%")&" for 3 or more. University groups get "&TEXT('College Inputs'!$B$41,"0%")&" instead, whichever is higher." -> Volume discount on licence fees: 10% for 2 licences, 15% for 3 or more. University groups get 15% instead, whichever is higher.
A75: ="Founding institutions (first "&'College Inputs'!$B$43&" colleges): "&TEXT('College Inputs'!$B$42,"0%")&" off, price locked for 3 years. Government colleges: "&TEXT('College Inputs'!$B$44,"0%")&" off. 3-year prepaid: "&TEXT('College Inputs'!$B$45,"0%")&" off and setup waived." -> Founding institutions (first 20 colleges): 25% off, price locked for 3 years. Government colleges: 20% off. 3-year prepaid: 10% off and setup waived.
A76: ="These commercial discounts stack but never exceed "&TEXT('College Inputs'!$B$46,"0%")&" in total. Renewal prices rise "&TEXT('College Inputs'!$B$47,"0%")&" a year (founding colleges excepted while locked)." -> These commercial discounts stack but never exceed 30% in total. Renewal prices rise 7% a year (founding colleges excepted while locked).
A77: ="Included supervisors, in-charges and admins are pooled across all of a college's licences: only the college total above the pool is charged." -> Included supervisors, in-charges and admins are pooled across all of a college's licences: only the college total above the pool is charged.
A78: ="If NDC raises a department's seats mid-year, the price holds until renewal; the tier is reset at renewal." -> If NDC raises a department's seats mid-year, the price holds until renewal; the tier is reset at renewal.
A79: ="Fair use: "&'College Inputs'!$B$50&" GB of images per licence; above that, extra storage is charged per 100 GB." -> Fair use: 250 GB of images per licence; above that, extra storage is charged per 100 GB.
A80: ="Licence covers patients treated in the college teaching hospital only. Faculty private practice needs a clinic plan." -> Licence covers patients treated in the college teaching hospital only. Faculty private practice needs a clinic plan.
A81: ="Data belongs to the college. Full export at any time, including after the licence ends." -> Data belongs to the college. Full export at any time, including after the licence ends.

Sheet College Quote Internal
A1: ="Implanr — Quote for "&IF(TRIM(B5)="","[College name]",B5) -> Implanr — Quote for Example Dental College
A2: INTERNAL — never send this sheet. Fill the yellow cells (blue text); everything else calculates from College Inputs. The college's copy is the College Quote Export tab, which fills itself from this sheet.
A4: COLLEGE DETAILS | F4: QUOTE DOCUMENT DETAILS (printed on the export)
A5: College name | B5: Example Dental College | F5: Quote reference | H5: IMP-Q-2026-001
A6: College type | B6: Private | F6: Quote date | H6: 46314
A7: University group buying for several colleges? | B7: No | F7: Valid for (days) | H7: 30
A8: Founding institution? | B8: Yes | F8: Valid until | H8: =H6+H7 -> 46344
A9: Contract term (years) | B9: 1 | C9: 3 = prepaid for 3 years: discount applies, setup fee waived. | F9: Prepared by | H9: Dr. Abhijit Patil
A10: New customer (setup fee applies)? | B10: Yes | F10: Designation | H10: Founder, Implanr, Prosthodontist and Implantologist
A11: Extra negotiated discount | B11: 0 | C11: Stacks with founding / government / 3-year up to the cap. | F11: Email | H11: info@implanr.com
A12: Research Module wanted? | B12: No | F12: Phone
A13: Fellows in Implantology (0 if none) | B13: 0 | F13: Payment terms | H13: 100% in advance, within 30 days of invoice
A14: Interns placing implants per year (0 if none) | B14: 60 | C14: Priced in tiers of 20 / 40 / 60 / 80 / 100. | F14: Website | H14: implanr.com
A16: LICENCES — one row per department, Centralised Implant Clinic or Unit (leave students at 0 for unused rows)
A17: Licence for | B17: PG students on roll (all 3 years) | C17: Tier | D17: Annual price (list) | E17: Extra PG students | F17: Extra student charge | G17: Supervisors incl. | H17: In-charges incl. | I17: Admins incl. | J17: Your cost (Rs / yr)
A18: Prosthodontics | B18: 12 | C18: =IF(B18<=0,"—",INDEX('College Inputs'!$A$6:$A$9,MATCH(B18,'College Inputs'!$C$6:$C$9,1))) -> Standard 12 | D18: =IF(B18<=0,0,INDEX('College Inputs'!$H$6:$H$9,MATCH(B18,'College Inputs'!$C$6:$C$9,1))) -> 60000 | E18: =IF(B18<=0,0,MAX(0,B18-'College Inputs'!$D$9)) -> 0 | F18: =E18*'College Inputs'!$B$16 -> 0 | G18: =IF(B18<=0,0,INDEX('College Inputs'!$E$6:$E$9,MATCH(B18,'College Inputs'!$C$6:$C$9,1))) -> 4 | H18: =IF(B18<=0,0,INDEX('College Inputs'!$F$6:$F$9,MATCH(B18,'College Inputs'!$C$6:$C$9,1))) -> 2 | I18: =IF(B18<=0,0,INDEX('College Inputs'!$G$6:$G$9,MATCH(B18,'College Inputs'!$C$6:$C$9,1))) -> 1 | J18: =IF(B18<=0,0,INDEX('College Inputs'!$J$6:$J$9,MATCH(B18,'College Inputs'!$C$6:$C$9,1))+E18*'College Inputs'!$C$16) -> 15000
A19: Periodontology | B19: 9 | C19: =IF(B19<=0,"—",INDEX('College Inputs'!$A$6:$A$9,MATCH(B19,'College Inputs'!$C$6:$C$9,1))) -> Essential 9 | D19: =IF(B19<=0,0,INDEX('College Inputs'!$H$6:$H$9,MATCH(B19,'College Inputs'!$C$6:$C$9,1))) -> 50000 | E19: =IF(B19<=0,0,MAX(0,B19-'College Inputs'!$D$9)) -> 0 | F19: =E19*'College Inputs'!$B$16 -> 0 | G19: =IF(B19<=0,0,INDEX('College Inputs'!$E$6:$E$9,MATCH(B19,'College Inputs'!$C$6:$C$9,1))) -> 3 | H19: =IF(B19<=0,0,INDEX('College Inputs'!$F$6:$F$9,MATCH(B19,'College Inputs'!$C$6:$C$9,1))) -> 1 | I19: =IF(B19<=0,0,INDEX('College Inputs'!$G$6:$G$9,MATCH(B19,'College Inputs'!$C$6:$C$9,1))) -> 1 | J19: =IF(B19<=0,0,INDEX('College Inputs'!$J$6:$J$9,MATCH(B19,'College Inputs'!$C$6:$C$9,1))+E19*'College Inputs'!$C$16) -> 12000
A20: Oral & Maxillofacial Surgery | B20: 9 | C20: =IF(B20<=0,"—",INDEX('College Inputs'!$A$6:$A$9,MATCH(B20,'College Inputs'!$C$6:$C$9,1))) -> Essential 9 | D20: =IF(B20<=0,0,INDEX('College Inputs'!$H$6:$H$9,MATCH(B20,'College Inputs'!$C$6:$C$9,1))) -> 50000 | E20: =IF(B20<=0,0,MAX(0,B20-'College Inputs'!$D$9)) -> 0 | F20: =E20*'College Inputs'!$B$16 -> 0 | G20: =IF(B20<=0,0,INDEX('College Inputs'!$E$6:$E$9,MATCH(B20,'College Inputs'!$C$6:$C$9,1))) -> 3 | H20: =IF(B20<=0,0,INDEX('College Inputs'!$F$6:$F$9,MATCH(B20,'College Inputs'!$C$6:$C$9,1))) -> 1 | I20: =IF(B20<=0,0,INDEX('College Inputs'!$G$6:$G$9,MATCH(B20,'College Inputs'!$C$6:$C$9,1))) -> 1 | J20: =IF(B20<=0,0,INDEX('College Inputs'!$J$6:$J$9,MATCH(B20,'College Inputs'!$C$6:$C$9,1))+E20*'College Inputs'!$C$16) -> 12000
A21: — | B21: 0 | C21: =IF(B21<=0,"—",INDEX('College Inputs'!$A$6:$A$9,MATCH(B21,'College Inputs'!$C$6:$C$9,1))) -> — | D21: =IF(B21<=0,0,INDEX('College Inputs'!$H$6:$H$9,MATCH(B21,'College Inputs'!$C$6:$C$9,1))) -> 0 | E21: =IF(B21<=0,0,MAX(0,B21-'College Inputs'!$D$9)) -> 0 | F21: =E21*'College Inputs'!$B$16 -> 0 | G21: =IF(B21<=0,0,INDEX('College Inputs'!$E$6:$E$9,MATCH(B21,'College Inputs'!$C$6:$C$9,1))) -> 0 | H21: =IF(B21<=0,0,INDEX('College Inputs'!$F$6:$F$9,MATCH(B21,'College Inputs'!$C$6:$C$9,1))) -> 0 | I21: =IF(B21<=0,0,INDEX('College Inputs'!$G$6:$G$9,MATCH(B21,'College Inputs'!$C$6:$C$9,1))) -> 0 | J21: =IF(B21<=0,0,INDEX('College Inputs'!$J$6:$J$9,MATCH(B21,'College Inputs'!$C$6:$C$9,1))+E21*'College Inputs'!$C$16) -> 0
A22: Total | B22: =SUM(B18:B21) -> 30 | C22: =COUNTIF(B18:B21,">0")&" licence(s)" -> 3 licence(s) | D22: =SUM(D18:D21) -> 160000 | E22: =SUM(E18:E21) -> 0 | F22: =SUM(F18:F21) -> 0 | G22: =SUM(G18:G21) -> 10 | H22: =SUM(H18:H21) -> 4 | I22: =SUM(I18:I21) -> 3 | J22: =SUM(J18:J21) -> 39000
A24: USERS — included allowances are pooled across all licences
A25: Role | B25: Included (all licences) | C25: Total the college needs | D25: Extra users | E25: Price / extra user | F25: Extra-user charge | G25: Your cost
A26: Supervisors / guides | B26: =G22 -> 10 | C26: 12 | D26: =MAX(0,C26-B26) -> 2 | E26: ='College Inputs'!$B$13 -> 3000 | F26: =D26*E26 -> 6000 | G26: =D26*'College Inputs'!$C$13 -> 600
A27: Implant in-charges | B27: =H22 -> 4 | C27: 4 | D27: =MAX(0,C27-B27) -> 0 | E27: ='College Inputs'!$B$14 -> 4000 | F27: =D27*E27 -> 0 | G27: =D27*'College Inputs'!$C$14 -> 0
A28: College admins | B28: =I22 -> 3 | C28: 2 | D28: =MAX(0,C28-B28) -> 0 | E28: ='College Inputs'!$B$15 -> 5000 | F28: =D28*E28 -> 0 | G28: =D28*'College Inputs'!$C$15 -> 0
A29: Management viewers (Dean, Principal, HOD) | B29: Free, read-only, up to 3 per college.
A31: QUOTE
A32: Licence fees (list, incl. extra students) | B32: =D22+F22 -> 160000
A33: Volume / group discount on licence fees | B33: =IF(B7="Yes",MAX('College Inputs'!$B$41,IF(COUNTIF(B18:B21,">0")>=3,'College Inputs'!$B$40,IF(COUNTIF(B18:B21,">0")=2,'College Inputs'!$B$39,0))),IF(COUNTIF(B18:B21,">0")>=3,'College Inputs'!$B$40,IF(COUNTIF(B18:B21,">0")=2,'College Inputs'!$B$39,0))) -> 0.15 | C33: 2 licences / 3 or more / university group.
A34: Licence fees after volume discount | B34: =B32*(1-B33) -> 136000
A35: Extra users | B35: =SUM(F26:F28) -> 6000
A36: Intern Programme tier | B36: =IF(B14<=0,"None",IF(B14>100,"Interns 100 + "&(B14-100)&" extra",INDEX('College Inputs'!$A$22:$A$26,MATCH(B14,'College Inputs'!$B$22:$B$26,1)))) -> Interns 60
A37: Intern Implant Programme | B37: =IF(B14<=0,0,IF(B14>100,'College Inputs'!$D$26+(B14-100)*'College Inputs'!$B$27,INDEX('College Inputs'!$D$22:$D$26,MATCH(B14,'College Inputs'!$B$22:$B$26,1)))) -> 40000
A38: Fellows | B38: =B13*'College Inputs'!$B$17 -> 0
A39: Research Module | B39: =IF(B12="Yes",'College Inputs'!$B$32,0) -> 0
A40: Annual subtotal | B40: =B34+B35+B37+B38+B39 -> 182000
A41: Commercial discount | B41: =MIN('College Inputs'!$B$46,IF(B8="Yes",'College Inputs'!$B$42,0)+IF(B6="Government",'College Inputs'!$B$44,0)+IF(B9=3,'College Inputs'!$B$45,0)+B11) -> 0.25 | C41: Founding + government + 3-year + negotiated, capped.
A42: Less: commercial discount | B42: =B40*B41 -> 45500
A43: Net annual fee (excl GST) | B43: =B40-B42 -> 136500 | C43: The number to quote.
A44: One-time onboarding & setup fee | B44: =IF(AND(B10="Yes",B9=1),'College Inputs'!$B$33,0) -> 25000 | C44: Waived on 3-year contracts.
A45: Invoice on signing (excl GST) | B45: =IF(B9=3,B43*3,B43)+B44 -> 161500 | C45: 3-year contracts are invoiced upfront.
A46: GST | B46: =B45*'College Inputs'!$B$48 -> 29070
A47: Invoice on signing (incl GST) | B47: =B45+B46 -> 190570
A48: Next year's renewal fee (excl GST) | B48: =IF(B9=3,"Prepaid — none due",IF(B8="Yes",B43,B43*(1+'College Inputs'!$B$47))) -> 136500 | C48: Founding colleges keep the same price for 3 years.
A49: Licence cost per PG per year | B49: =IF(B22=0,0,B34*(1-B41)/B22) -> 3400 | C49: A useful line for the Dean.
A51: YOUR MARGIN — internal, do not show the college
A52: Your running cost per year | B52: =J22+SUM(G26:G28)+B14*'College Inputs'!$B$28+B13*'College Inputs'!$C$17+IF(B12="Yes",'College Inputs'!$C$32,0)+'College Inputs'!$C$34 -> 51800 | C52: Licences + extra users + interns + fellows + research + yearly retraining.
A53: First-year onboarding travel | B53: =IF(B10="Yes",'College Inputs'!$C$33,0) -> 15000
A54: Year-1 gross profit | B54: =B43+B44-B52-B53 -> 94700
A55: Year-1 gross margin | B55: =IF((B43+B44)=0,0,B54/(B43+B44)) -> 0.58637771
A56: Ongoing gross margin (year 2 onward) | B56: =IF(B43=0,0,(B43-B52)/B43) -> 0.62051282
A57: Quote check | B57: =IF(B56>='College Inputs'!$B$49,"OK — above minimum margin","Below minimum margin — reduce the discount") -> OK — above minimum margin
A59: WORDING USED ON THE EXPORT (automatic — no need to edit)
A60: Volume discount wording | B60: =IF(B33=0,"",IF(AND(B7="Yes",B33='College Inputs'!$B$41),"University group discount","Multi-department discount")&" ("&TEXT(B33,"0%")&")") -> Multi-department discount (15%)
A61: Commercial discount parts | B61: =IF(B8="Yes","Founding institution, ","")&IF(B6="Government","Government college, ","")&IF(B9=3,"3-year prepaid, ","")&IF(B11>0,"Special discount, ","") -> Founding institution,
A62: Commercial discount wording | B62: =IF(OR(B41=0,B61=""),"","Discount — "&LEFT(B61,LEN(B61)-2)&" ("&TEXT(B41,"0%")&")") -> Discount — Founding institution (25%)
A63: Contract term wording | B63: =IF(B9=3,"3 years, prepaid","1 year, renewable annually") -> 1 year, renewable annually

Sheet College Quote Export
A1: ='College Quote Internal'!A1 -> Implanr — Quote for Example Dental College
A2: AI-assisted digital platform for dental implant case planning, supervised clinical training, documentation and long-term outcome surveillance
A4: Prepared for | B4: ='College Quote Internal'!B5 -> Example Dental College | D4: Quote reference | E4: ='College Quote Internal'!H5 -> IMP-Q-2026-001
A5: Contract term | B5: ='College Quote Internal'!B63 -> 1 year, renewable annually | D5: Quote date | E5: ='College Quote Internal'!H6 -> 46314
A6: Licences | B6: =COUNTIF('College Quote Internal'!B18:B21,">0")&" licence(s) · "&'College Quote Internal'!B22&" PG students" -> 3 licence(s) · 30 PG students | D6: Valid until | E6: ='College Quote Internal'!H8 -> 46344
A7: Prepared by | B7: ='College Quote Internal'!H9&", "&'College Quote Internal'!H10 -> Dr. Abhijit Patil, Founder, Implanr, Prosthodontist and Implantologist | D7: Contact | E7: ='College Quote Internal'!H11&IF(TRIM('College Quote Internal'!H12)="",""," · "&'College Quote Internal'!H12)&" · "&'College Quote Internal'!H14 -> info@implanr.com · implanr.com
A9: 1. LICENCES
A10: Licence for | B10: PG students (all 3 years) | C10: Tier | D10: Users included (supervisors / in-charges / admins) | E10: Annual price
A11: =IF('College Quote Internal'!B18<=0,"",'College Quote Internal'!A18) -> Prosthodontics | B11: =IF('College Quote Internal'!B18<=0,"",'College Quote Internal'!B18) -> 12 | C11: =IF('College Quote Internal'!B18<=0,"",'College Quote Internal'!C18&IF('College Quote Internal'!E18>0," + "&'College Quote Internal'!E18&" extra PGs","")) -> Standard 12 | D11: =IF('College Quote Internal'!B18<=0,"",'College Quote Internal'!G18&" / "&'College Quote Internal'!H18&" / "&'College Quote Internal'!I18) -> 4 / 2 / 1 | E11: =IF('College Quote Internal'!B18<=0,"",'College Quote Internal'!D18+'College Quote Internal'!F18) -> 60000
A12: =IF('College Quote Internal'!B19<=0,"",'College Quote Internal'!A19) -> Periodontology | B12: =IF('College Quote Internal'!B19<=0,"",'College Quote Internal'!B19) -> 9 | C12: =IF('College Quote Internal'!B19<=0,"",'College Quote Internal'!C19&IF('College Quote Internal'!E19>0," + "&'College Quote Internal'!E19&" extra PGs","")) -> Essential 9 | D12: =IF('College Quote Internal'!B19<=0,"",'College Quote Internal'!G19&" / "&'College Quote Internal'!H19&" / "&'College Quote Internal'!I19) -> 3 / 1 / 1 | E12: =IF('College Quote Internal'!B19<=0,"",'College Quote Internal'!D19+'College Quote Internal'!F19) -> 50000
A13: =IF('College Quote Internal'!B20<=0,"",'College Quote Internal'!A20) -> Oral & Maxillofacial Surgery | B13: =IF('College Quote Internal'!B20<=0,"",'College Quote Internal'!B20) -> 9 | C13: =IF('College Quote Internal'!B20<=0,"",'College Quote Internal'!C20&IF('College Quote Internal'!E20>0," + "&'College Quote Internal'!E20&" extra PGs","")) -> Essential 9 | D13: =IF('College Quote Internal'!B20<=0,"",'College Quote Internal'!G20&" / "&'College Quote Internal'!H20&" / "&'College Quote Internal'!I20) -> 3 / 1 / 1 | E13: =IF('College Quote Internal'!B20<=0,"",'College Quote Internal'!D20+'College Quote Internal'!F20) -> 50000
A14: =IF('College Quote Internal'!B21<=0,"",'College Quote Internal'!A21) | B14: =IF('College Quote Internal'!B21<=0,"",'College Quote Internal'!B21) | C14: =IF('College Quote Internal'!B21<=0,"",'College Quote Internal'!C21&IF('College Quote Internal'!E21>0," + "&'College Quote Internal'!E21&" extra PGs","")) | D14: =IF('College Quote Internal'!B21<=0,"",'College Quote Internal'!G21&" / "&'College Quote Internal'!H21&" / "&'College Quote Internal'!I21) | E14: =IF('College Quote Internal'!B21<=0,"",'College Quote Internal'!D21+'College Quote Internal'!F21)
A15: Total | B15: ='College Quote Internal'!B22 -> 30 | C15: ='College Quote Internal'!C22 -> 3 licence(s) | D15: ='College Quote Internal'!G22&" / "&'College Quote Internal'!H22&" / "&'College Quote Internal'!I22 -> 10 / 4 / 3 | E15: ='College Quote Internal'!B32 -> 160000
A17: 2. USERS
A18: Role | B18: Included | C18: Requested | D18: Additional users | E18: Annual charge
A19: Supervisors / guides | B19: ='College Quote Internal'!B26 -> 10 | C19: ='College Quote Internal'!C26 -> 12 | D19: ='College Quote Internal'!D26 -> 2 | E19: =IF('College Quote Internal'!F26=0,"Nil",'College Quote Internal'!F26) -> 6000
A20: Implant in-charges | B20: ='College Quote Internal'!B27 -> 4 | C20: ='College Quote Internal'!C27 -> 4 | D20: ='College Quote Internal'!D27 -> 0 | E20: =IF('College Quote Internal'!F27=0,"Nil",'College Quote Internal'!F27) -> Nil
A21: College admins | B21: ='College Quote Internal'!B28 -> 3 | C21: ='College Quote Internal'!C28 -> 2 | D21: ='College Quote Internal'!D28 -> 0 | E21: =IF('College Quote Internal'!F28=0,"Nil",'College Quote Internal'!F28) -> Nil
A22: Management viewers (Dean, Principal, HOD) | B22: 3 | D22: Read-only | E22: Free
A24: 3. ADD-ONS
A25: Add-on | B25: Selection | E25: Annual charge
A26: Intern Implant Programme | B26: =IF('College Quote Internal'!B14<=0,"Not selected",'College Quote Internal'!B36&" — "&'College Quote Internal'!B14&" interns placing implants under supervision") -> Interns 60 — 60 interns placing implants under supervision | E26: =IF('College Quote Internal'!B37=0,"",'College Quote Internal'!B37) -> 40000
A27: Fellows in Implantology | B27: =IF('College Quote Internal'!B13<=0,"Not selected",'College Quote Internal'!B13&" fellow(s)") -> Not selected | E27: =IF('College Quote Internal'!B38=0,"",'College Quote Internal'!B38)
A28: Research Module | B28: =IF('College Quote Internal'!B12="Yes","Selected — dissertation studies inside the case records","Not selected") -> Not selected | E28: =IF('College Quote Internal'!B39=0,"",'College Quote Internal'!B39)
A29: Interns who only observe or assist on cases are included free.
A31: 4. PRICE SUMMARY (per year, unless stated)
A32: Licence fees (list price) | E32: ='College Quote Internal'!B32 -> 160000
A33: =IF('College Quote Internal'!B60="","Multi-department discount",'College Quote Internal'!B60) -> Multi-department discount (15%) | E33: =IF('College Quote Internal'!B33=0,"Nil","– Rs "&TEXT('College Quote Internal'!B32*'College Quote Internal'!B33,"[>=100000]##\,##\,##0;##,##0")) -> – Rs 24,000
A34: Licence fees after discount | E34: ='College Quote Internal'!B34 -> 136000
A35: Additional users | E35: ='College Quote Internal'!B35 -> 6000
A36: Add-ons (interns, fellows, Research Module) | E36: ='College Quote Internal'!B37+'College Quote Internal'!B38+'College Quote Internal'!B39 -> 40000
A37: Annual subtotal | E37: ='College Quote Internal'!B40 -> 182000
A38: =IF('College Quote Internal'!B62="","Discount",'College Quote Internal'!B62) -> Discount — Founding institution (25%) | E38: =IF('College Quote Internal'!B41=0,"Nil","– Rs "&TEXT('College Quote Internal'!B42,"[>=100000]##\,##\,##0;##,##0")) -> – Rs 45,500
A39: Net annual fee (excl GST) | E39: ='College Quote Internal'!B43 -> 136500
A40: One-time onboarding & setup fee | E40: =IF('College Quote Internal'!B44=0,IF('College Quote Internal'!B9=3,"Waived (3-year contract)","Nil"),'College Quote Internal'!B44) -> 25000
A41: =IF('College Quote Internal'!B9=3,"Amount payable on signing — 3 years prepaid (excl GST)","Amount payable on signing (excl GST)") -> Amount payable on signing (excl GST) | E41: ='College Quote Internal'!B45 -> 161500
A42: ="GST @ "&TEXT('College Inputs'!$B$48,"0%") -> GST @ 18% | E42: ='College Quote Internal'!B46 -> 29070
A43: Total payable on signing (incl GST) | E43: ='College Quote Internal'!B47 -> 190570
A44: Renewal fee for the following year (excl GST) | E44: =IF('College Quote Internal'!B9=3,"Not applicable — prepaid for 3 years",'College Quote Internal'!B48) -> 136500
A45: Works out to, per PG student per year (licence fees) | E45: ='College Quote Internal'!B49 -> 3400
A47: 5. WHAT IS INCLUDED IN EVERY LICENCE
A48: • Implant case record across all 5 phases — unlimited cases | C48: • iOS and Android apps; CBCT upload and viewing
A49: • AI-assisted treatment planning and case summaries | C49: • Supervisor approval at every phase, with an immutable audit trail
A50: • PDF reports and automatic lab prescriptions | C50: • Lifetime maintenance recalls and outcome tracking
A51: • Unit and college dashboards; full data export at any time | C51: • Onboarding in person and remotely; retraining for every new PG batch
A53: 6. TERMS
A54: ="All prices are in Indian rupees and exclude GST, which is charged at "&TEXT('College Inputs'!$B$48,"0%")&"." -> All prices are in Indian rupees and exclude GST, which is charged at 18%.
A55: ="This quotation is valid until "&TEXT('College Quote Internal'!H8,"dd mmm yyyy")&"." -> This quotation is valid until 18 Nov 2026.
A56: ="Payment: "&'College Quote Internal'!H13&"." -> Payment: 100% in advance, within 30 days of invoice.
A57: ="Licences are billed annually in advance, aligned to the start of the MDS academic session; the first year may be pro-rated." -> Licences are billed annually in advance, aligned to the start of the MDS academic session; the first year may be pro-rated.
A58: =IF('College Quote Internal'!B9=3,"Three-year contract: prepaid, with the price fixed for the full term.",IF('College Quote Internal'!B8="Yes","Founding-institution price is held for 3 years from the start date.","Renewal prices may rise by up to "&TEXT('College Inputs'!$B$47,"0%")&" a year.")) -> Founding-institution price is held for 3 years from the start date.
A59: ="Supervisor, in-charge and admin allowances are pooled across all licences. Additional users can be added during the year at the per-user rate." -> Supervisor, in-charge and admin allowances are pooled across all licences. Additional users can be added during the year at the per-user rate.
A60: ="Fair use: "&'College Inputs'!$B$50&" GB of images per licence; additional storage is available on request." -> Fair use: 250 GB of images per licence; additional storage is available on request.
A61: ="The licence covers patients treated in the college teaching hospital." -> The licence covers patients treated in the college teaching hospital.
A62: ="All clinical data belongs to the college and can be exported in full at any time, including after the licence ends." -> All clinical data belongs to the college and can be exported in full at any time, including after the licence ends.
A64: ACCEPTANCE
A65: For Implanr | C65: ="For "&IF(TRIM('College Quote Internal'!B5)="","the college",'College Quote Internal'!B5) -> For Example Dental College
A66: ="Name: "&'College Quote Internal'!H9&", "&'College Quote Internal'!H10 -> Name: Dr. Abhijit Patil, Founder, Implanr, Prosthodontist and Implantologist | C66: Name and designation:
A67: Signature: | C67: Signature and seal:
A68: Date: | C68: Date:

Sheet College Revenue Model
A1: Implanr — College revenue and payback model (5 years, three scenarios)
A2: Money in Rs lakh, excluding GST, before income tax. Every number comes from College Inputs: change it there, not here.
A4: SUMMARY
A5: Scenario | B5: Active colleges Y1 | C5: Active colleges Y3 | D5: Active colleges Y5 | E5: Revenue Y3 (Rs lakh) | F5: Net profit Y3 (Rs lakh) | G5: 5-year net profit (Rs lakh) | H5: Rs 10 lakh recovered in
A6: Conservative | B6: =B20 -> 5 | C6: =D20 -> 27 | D6: =F20 -> 47 | E6: =D31 -> 53.582128 | F6: =D39 -> 35.284858 | G6: =F40 -> 186.77133 | H6: =IF(B41>=0,"Year 1",IF(C41>=0,"Year 2",IF(D41>=0,"Year 3",IF(E41>=0,"Year 4",IF(F41>=0,"Year 5","Beyond Year 5"))))) -> Year 2
A7: Base | B7: =B48 -> 10 | C7: =D48 -> 55 | D7: =F48 -> 95 | E7: =D59 -> 109.07933 | F7: =D67 -> 74.973785 | G7: =F68 -> 394.41957 | H7: =IF(B69>=0,"Year 1",IF(C69>=0,"Year 2",IF(D69>=0,"Year 3",IF(E69>=0,"Year 4",IF(F69>=0,"Year 5","Beyond Year 5"))))) -> Year 2
A8: Optimistic | B8: =B76 -> 20 | C8: =D76 -> 94 | D8: =F76 -> 161 | E8: =D87 -> 186.26741 | F8: =D95 -> 130.23247 | G8: =F96 -> 685.31538 | H8: =IF(B97>=0,"Year 1",IF(C97>=0,"Year 2",IF(D97>=0,"Year 3",IF(E97>=0,"Year 4",IF(F97>=0,"Year 5","Beyond Year 5"))))) -> Year 1
A10: Gross profit per active college per year (base, Year 3, Rs lakh) | B10: =IF(D48=0,0,D64/D48) -> 1.4177052
A11: Active colleges needed just to cover fixed expenses | B11: =IF(B10=0,0,ROUNDUP(('College Inputs'!$B$55/100000)/B10,0)) -> 3
A12: Active colleges needed to cover fixed expenses AND repay Rs 10 lakh in one year | B12: =IF(B10=0,0,ROUNDUP((('College Inputs'!$B$55+'College Inputs'!$B$54)/100000)/B10,0)) -> 10
A13: Market ceiling: all 289 colleges at the base Year-3 revenue per college (Rs lakh / year) | B13: =IF(D48=0,0,'College Inputs'!$B$57*D59/D48) -> 573.16232
A16: CONSERVATIVE SCENARIO
A17: Rs lakh unless stated | B17: Year 1 | C17: Year 2 | D17: Year 3 | E17: Year 4 | F17: Year 5
A18: New colleges signed | B18: ='College Inputs'!B86 -> 5 | C18: ='College Inputs'!C86 -> 10 | D18: ='College Inputs'!D86 -> 15 | E18: ='College Inputs'!E86 -> 15 | F18: ='College Inputs'!F86 -> 15
A19: Renewing colleges | B19: =0 -> 0 | C19: =ROUND(B20*'College Inputs'!$B$56,0) -> 4 | D19: =ROUND(C20*'College Inputs'!$B$56,0) -> 12 | E19: =ROUND(D20*'College Inputs'!$B$56,0) -> 23 | F19: =ROUND(E20*'College Inputs'!$B$56,0) -> 32
A20: Active colleges | B20: =MIN('College Inputs'!$B$57,B18+B19) -> 5 | C20: =MIN('College Inputs'!$B$57,C18+C19) -> 14 | D20: =MIN('College Inputs'!$B$57,D18+D19) -> 27 | E20: =MIN('College Inputs'!$B$57,E18+E19) -> 38 | F20: =MIN('College Inputs'!$B$57,F18+F19) -> 47
A21: Price index (annual increase) | B21: =1 -> 1 | C21: =B21*(1+'College Inputs'!$B$47) -> 1.07 | D21: =C21*(1+'College Inputs'!$B$47) -> 1.1449 | E21: =D21*(1+'College Inputs'!$B$47) -> 1.225043 | F21: =E21*(1+'College Inputs'!$B$47) -> 1.310796
A22: Average licence fees per college (Rs, after volume discount) | B22: ='College Inputs'!$B$58*SUMPRODUCT('College Inputs'!$B$68:$B$71,'College Inputs'!$H$6:$H$9)*(1-'College Inputs'!$B$59)*B21 -> 147400 | C22: ='College Inputs'!$B$58*SUMPRODUCT('College Inputs'!$B$68:$B$71,'College Inputs'!$H$6:$H$9)*(1-'College Inputs'!$B$59)*C21 -> 157718 | D22: ='College Inputs'!$B$58*SUMPRODUCT('College Inputs'!$B$68:$B$71,'College Inputs'!$H$6:$H$9)*(1-'College Inputs'!$B$59)*D21 -> 168758.26 | E22: ='College Inputs'!$B$58*SUMPRODUCT('College Inputs'!$B$68:$B$71,'College Inputs'!$H$6:$H$9)*(1-'College Inputs'!$B$59)*E21 -> 180571.34 | F22: ='College Inputs'!$B$58*SUMPRODUCT('College Inputs'!$B$68:$B$71,'College Inputs'!$H$6:$H$9)*(1-'College Inputs'!$B$59)*F21 -> 193211.33
A23: Average extra-user charges per college (Rs) | B23: ='College Inputs'!$B$60*B21 -> 9000 | C23: ='College Inputs'!$B$60*C21 -> 9630 | D23: ='College Inputs'!$B$60*D21 -> 10304.1 | E23: ='College Inputs'!$B$60*E21 -> 11025.387 | F23: ='College Inputs'!$B$60*F21 -> 11797.164
A24: Average Intern Programme price (Rs) | B24: =SUMPRODUCT('College Inputs'!$B$75:$B$79,'College Inputs'!$D$22:$D$26)*B21 -> 45200 | C24: =SUMPRODUCT('College Inputs'!$B$75:$B$79,'College Inputs'!$D$22:$D$26)*C21 -> 48364 | D24: =SUMPRODUCT('College Inputs'!$B$75:$B$79,'College Inputs'!$D$22:$D$26)*D21 -> 51749.48 | E24: =SUMPRODUCT('College Inputs'!$B$75:$B$79,'College Inputs'!$D$22:$D$26)*E21 -> 55371.944 | F24: =SUMPRODUCT('College Inputs'!$B$75:$B$79,'College Inputs'!$D$22:$D$26)*F21 -> 59247.98
A25: Average commercial discount | B25: ='College Inputs'!B83 -> 0.25 | C25: ='College Inputs'!C83 -> 0.18 | D25: ='College Inputs'!D83 -> 0.12 | E25: ='College Inputs'!E83 -> 0.1 | F25: ='College Inputs'!F83 -> 0.1
A26: Licence + extra-user revenue | B26: =B20*(B22+B23)*(1-B25)/100000 -> 5.865 | C26: =C20*(C22+C23)*(1-C25)/100000 -> 19.21155 | D26: =D20*(D22+D23)*(1-D25)/100000 -> 42.545217 | E26: =E20*(E22+E23)*(1-E25)/100000 -> 65.52608 | F26: =F20*(F22+F23)*(1-F25)/100000 -> 86.718594
A27: Intern Programme revenue | B27: =B20*'College Inputs'!$B$61*B24*(1-B25)/100000 -> 0.678 | C27: =C20*'College Inputs'!$B$61*C24*(1-C25)/100000 -> 2.2208749 | D27: =D20*'College Inputs'!$B$61*D24*(1-D25)/100000 -> 4.9182706 | E27: =E20*'College Inputs'!$B$61*E24*(1-E25)/100000 -> 7.5748819 | F27: =F20*'College Inputs'!$B$61*F24*(1-F25)/100000 -> 10.024758
A28: Research Module revenue | B28: =B20*'College Inputs'!$B$62*'College Inputs'!$B$32*B21*(1-B25)/100000 -> 0.45 | C28: =C20*'College Inputs'!$B$62*'College Inputs'!$B$32*C21*(1-C25)/100000 -> 1.474032 | D28: =D20*'College Inputs'!$B$62*'College Inputs'!$B$32*D21*(1-D25)/100000 -> 3.2643389 | E28: =E20*'College Inputs'!$B$62*'College Inputs'!$B$32*E21*(1-E25)/100000 -> 5.0275765 | F28: =F20*'College Inputs'!$B$62*'College Inputs'!$B$32*F21*(1-F25)/100000 -> 6.6536005
A29: Fellowship revenue | B29: =B20*'College Inputs'!$B$63*'College Inputs'!$B$64*'College Inputs'!$B$17*B21*(1-B25)/100000 -> 0.135 | C29: =C20*'College Inputs'!$B$63*'College Inputs'!$B$64*'College Inputs'!$B$17*C21*(1-C25)/100000 -> 0.4422096 | D29: =D20*'College Inputs'!$B$63*'College Inputs'!$B$64*'College Inputs'!$B$17*D21*(1-D25)/100000 -> 0.97930166 | E29: =E20*'College Inputs'!$B$63*'College Inputs'!$B$64*'College Inputs'!$B$17*E21*(1-E25)/100000 -> 1.5082729 | F29: =F20*'College Inputs'!$B$63*'College Inputs'!$B$64*'College Inputs'!$B$17*F21*(1-F25)/100000 -> 1.9960802
A30: Setup fees | B30: =B18*'College Inputs'!$B$65*'College Inputs'!$B$33/100000 -> 0.625 | C30: =C18*'College Inputs'!$B$65*'College Inputs'!$B$33/100000 -> 1.25 | D30: =D18*'College Inputs'!$B$65*'College Inputs'!$B$33/100000 -> 1.875 | E30: =E18*'College Inputs'!$B$65*'College Inputs'!$B$33/100000 -> 1.875 | F30: =F18*'College Inputs'!$B$65*'College Inputs'!$B$33/100000 -> 1.875
A31: TOTAL REVENUE | B31: =SUM(B26:B30) -> 7.753 | C31: =SUM(C26:C30) -> 24.598667 | D31: =SUM(D26:D30) -> 53.582128 | E31: =SUM(E26:E30) -> 81.511811 | F31: =SUM(F26:F30) -> 107.26803
A32: Licence running cost | B32: =B20*'College Inputs'!$B$58*SUMPRODUCT('College Inputs'!$B$68:$B$71,'College Inputs'!$J$6:$J$9)/100000 -> 2.00625 | C32: =C20*'College Inputs'!$B$58*SUMPRODUCT('College Inputs'!$B$68:$B$71,'College Inputs'!$J$6:$J$9)/100000 -> 5.6175 | D32: =D20*'College Inputs'!$B$58*SUMPRODUCT('College Inputs'!$B$68:$B$71,'College Inputs'!$J$6:$J$9)/100000 -> 10.83375 | E32: =E20*'College Inputs'!$B$58*SUMPRODUCT('College Inputs'!$B$68:$B$71,'College Inputs'!$J$6:$J$9)/100000 -> 15.2475 | F32: =F20*'College Inputs'!$B$58*SUMPRODUCT('College Inputs'!$B$68:$B$71,'College Inputs'!$J$6:$J$9)/100000 -> 18.85875
A33: Add-on running cost | B33: =B20*('College Inputs'!$B$61*SUMPRODUCT('College Inputs'!$B$75:$B$79,'College Inputs'!$F$22:$F$26)+'College Inputs'!$B$62*'College Inputs'!$C$32+'College Inputs'!$B$63*'College Inputs'!$B$64*'College Inputs'!$C$17)/100000 -> 0.2988 | C33: =C20*('College Inputs'!$B$61*SUMPRODUCT('College Inputs'!$B$75:$B$79,'College Inputs'!$F$22:$F$26)+'College Inputs'!$B$62*'College Inputs'!$C$32+'College Inputs'!$B$63*'College Inputs'!$B$64*'College Inputs'!$C$17)/100000 -> 0.83664 | D33: =D20*('College Inputs'!$B$61*SUMPRODUCT('College Inputs'!$B$75:$B$79,'College Inputs'!$F$22:$F$26)+'College Inputs'!$B$62*'College Inputs'!$C$32+'College Inputs'!$B$63*'College Inputs'!$B$64*'College Inputs'!$C$17)/100000 -> 1.61352 | E33: =E20*('College Inputs'!$B$61*SUMPRODUCT('College Inputs'!$B$75:$B$79,'College Inputs'!$F$22:$F$26)+'College Inputs'!$B$62*'College Inputs'!$C$32+'College Inputs'!$B$63*'College Inputs'!$B$64*'College Inputs'!$C$17)/100000 -> 2.27088 | F33: =F20*('College Inputs'!$B$61*SUMPRODUCT('College Inputs'!$B$75:$B$79,'College Inputs'!$F$22:$F$26)+'College Inputs'!$B$62*'College Inputs'!$C$32+'College Inputs'!$B$63*'College Inputs'!$B$64*'College Inputs'!$C$17)/100000 -> 2.80872
A34: Onboarding travel (new colleges) | B34: =B18*'College Inputs'!$C$33/100000 -> 0.75 | C34: =C18*'College Inputs'!$C$33/100000 -> 1.5 | D34: =D18*'College Inputs'!$C$33/100000 -> 2.25 | E34: =E18*'College Inputs'!$C$33/100000 -> 2.25 | F34: =F18*'College Inputs'!$C$33/100000 -> 2.25
A35: Retraining visits (renewing colleges) | B35: =B19*'College Inputs'!$C$34/100000 -> 0 | C35: =C19*'College Inputs'!$C$34/100000 -> 0.2 | D35: =D19*'College Inputs'!$C$34/100000 -> 0.6 | E35: =E19*'College Inputs'!$C$34/100000 -> 1.15 | F35: =F19*'College Inputs'!$C$34/100000 -> 1.6
A36: GROSS PROFIT | B36: =B31-SUM(B32:B35) -> 4.69795 | C36: =C31-SUM(C32:C35) -> 16.444527 | D36: =D31-SUM(D32:D35) -> 38.284858 | E36: =E31-SUM(E32:E35) -> 60.593431 | F36: =F31-SUM(F32:F35) -> 81.750563
A37: Gross margin | B37: =IF(B31=0,0,B36/B31) -> 0.60595253 | C37: =IF(C31=0,0,C36/C31) -> 0.66851293 | D37: =IF(D31=0,0,D36/D31) -> 0.71450798 | E37: =IF(E31=0,0,E36/E31) -> 0.74336995 | F37: =IF(F31=0,0,F36/F31) -> 0.76211487
A38: Other fixed expenses | B38: ='College Inputs'!$B$55/100000 -> 3 | C38: ='College Inputs'!$B$55/100000 -> 3 | D38: ='College Inputs'!$B$55/100000 -> 3 | E38: ='College Inputs'!$B$55/100000 -> 3 | F38: ='College Inputs'!$B$55/100000 -> 3
A39: NET PROFIT (before tax) | B39: =B36-B38 -> 1.69795 | C39: =C36-C38 -> 13.444527 | D39: =D36-D38 -> 35.284858 | E39: =E36-E38 -> 57.593431 | F39: =F36-F38 -> 78.750563
A40: Cumulative net profit | B40: =B39 -> 1.69795 | C40: =B40+C39 -> 15.142477 | D40: =C40+D39 -> 50.427335 | E40: =D40+E39 -> 108.02077 | F40: =E40+F39 -> 186.77133
A41: Position after recovering the Rs 10 lakh investment | B41: =B40-'College Inputs'!$B$54/100000 -> -8.30205 | C41: =C40-'College Inputs'!$B$54/100000 -> 5.1424769 | D41: =D40-'College Inputs'!$B$54/100000 -> 40.427335 | E41: =E40-'College Inputs'!$B$54/100000 -> 98.020766 | F41: =F40-'College Inputs'!$B$54/100000 -> 176.77133
A44: BASE SCENARIO
A45: Rs lakh unless stated | B45: Year 1 | C45: Year 2 | D45: Year 3 | E45: Year 4 | F45: Year 5
A46: New colleges signed | B46: ='College Inputs'!B87 -> 10 | C46: ='College Inputs'!C87 -> 20 | D46: ='College Inputs'!D87 -> 30 | E46: ='College Inputs'!E87 -> 30 | F46: ='College Inputs'!F87 -> 30
A47: Renewing colleges | B47: =0 -> 0 | C47: =ROUND(B48*'College Inputs'!$B$56,0) -> 9 | D47: =ROUND(C48*'College Inputs'!$B$56,0) -> 25 | E47: =ROUND(D48*'College Inputs'!$B$56,0) -> 47 | F47: =ROUND(E48*'College Inputs'!$B$56,0) -> 65
A48: Active colleges | B48: =MIN('College Inputs'!$B$57,B46+B47) -> 10 | C48: =MIN('College Inputs'!$B$57,C46+C47) -> 29 | D48: =MIN('College Inputs'!$B$57,D46+D47) -> 55 | E48: =MIN('College Inputs'!$B$57,E46+E47) -> 77 | F48: =MIN('College Inputs'!$B$57,F46+F47) -> 95
A49: Price index (annual increase) | B49: =1 -> 1 | C49: =B49*(1+'College Inputs'!$B$47) -> 1.07 | D49: =C49*(1+'College Inputs'!$B$47) -> 1.1449 | E49: =D49*(1+'College Inputs'!$B$47) -> 1.225043 | F49: =E49*(1+'College Inputs'!$B$47) -> 1.310796
A50: Average licence fees per college (Rs, after volume discount) | B50: ='College Inputs'!$B$58*SUMPRODUCT('College Inputs'!$B$68:$B$71,'College Inputs'!$H$6:$H$9)*(1-'College Inputs'!$B$59)*B49 -> 147400 | C50: ='College Inputs'!$B$58*SUMPRODUCT('College Inputs'!$B$68:$B$71,'College Inputs'!$H$6:$H$9)*(1-'College Inputs'!$B$59)*C49 -> 157718 | D50: ='College Inputs'!$B$58*SUMPRODUCT('College Inputs'!$B$68:$B$71,'College Inputs'!$H$6:$H$9)*(1-'College Inputs'!$B$59)*D49 -> 168758.26 | E50: ='College Inputs'!$B$58*SUMPRODUCT('College Inputs'!$B$68:$B$71,'College Inputs'!$H$6:$H$9)*(1-'College Inputs'!$B$59)*E49 -> 180571.34 | F50: ='College Inputs'!$B$58*SUMPRODUCT('College Inputs'!$B$68:$B$71,'College Inputs'!$H$6:$H$9)*(1-'College Inputs'!$B$59)*F49 -> 193211.33
A51: Average extra-user charges per college (Rs) | B51: ='College Inputs'!$B$60*B49 -> 9000 | C51: ='College Inputs'!$B$60*C49 -> 9630 | D51: ='College Inputs'!$B$60*D49 -> 10304.1 | E51: ='College Inputs'!$B$60*E49 -> 11025.387 | F51: ='College Inputs'!$B$60*F49 -> 11797.164
A52: Average Intern Programme price (Rs) | B52: =SUMPRODUCT('College Inputs'!$B$75:$B$79,'College Inputs'!$D$22:$D$26)*B49 -> 45200 | C52: =SUMPRODUCT('College Inputs'!$B$75:$B$79,'College Inputs'!$D$22:$D$26)*C49 -> 48364 | D52: =SUMPRODUCT('College Inputs'!$B$75:$B$79,'College Inputs'!$D$22:$D$26)*D49 -> 51749.48 | E52: =SUMPRODUCT('College Inputs'!$B$75:$B$79,'College Inputs'!$D$22:$D$26)*E49 -> 55371.944 | F52: =SUMPRODUCT('College Inputs'!$B$75:$B$79,'College Inputs'!$D$22:$D$26)*F49 -> 59247.98
A53: Average commercial discount | B53: ='College Inputs'!B83 -> 0.25 | C53: ='College Inputs'!C83 -> 0.18 | D53: ='College Inputs'!D83 -> 0.12 | E53: ='College Inputs'!E83 -> 0.1 | F53: ='College Inputs'!F83 -> 0.1
A54: Licence + extra-user revenue | B54: =B48*(B50+B51)*(1-B53)/100000 -> 11.73 | C54: =C48*(C50+C51)*(1-C53)/100000 -> 39.795354 | D54: =D48*(D50+D51)*(1-D53)/100000 -> 86.666182 | E54: =E48*(E50+E51)*(1-E53)/100000 -> 132.77653 | F54: =F48*(F50+F51)*(1-F53)/100000 -> 175.28226
A55: Intern Programme revenue | B55: =B48*'College Inputs'!$B$61*B52*(1-B53)/100000 -> 1.356 | C55: =C48*'College Inputs'!$B$61*C52*(1-C53)/100000 -> 4.6003837 | D55: =D48*'College Inputs'!$B$61*D52*(1-D53)/100000 -> 10.018699 | E55: =E48*'College Inputs'!$B$61*E52*(1-E53)/100000 -> 15.349103 | F55: =F48*'College Inputs'!$B$61*F52*(1-F53)/100000 -> 20.262809
A56: Research Module revenue | B56: =B48*'College Inputs'!$B$62*'College Inputs'!$B$32*B49*(1-B53)/100000 -> 0.9 | C56: =C48*'College Inputs'!$B$62*'College Inputs'!$B$32*C49*(1-C53)/100000 -> 3.053352 | D56: =D48*'College Inputs'!$B$62*'College Inputs'!$B$32*D49*(1-D53)/100000 -> 6.6495792 | E56: =E48*'College Inputs'!$B$62*'College Inputs'!$B$32*E49*(1-E53)/100000 -> 10.187458 | F56: =F48*'College Inputs'!$B$62*'College Inputs'!$B$32*F49*(1-F53)/100000 -> 13.448767
A57: Fellowship revenue | B57: =B48*'College Inputs'!$B$63*'College Inputs'!$B$64*'College Inputs'!$B$17*B49*(1-B53)/100000 -> 0.27 | C57: =C48*'College Inputs'!$B$63*'College Inputs'!$B$64*'College Inputs'!$B$17*C49*(1-C53)/100000 -> 0.9160056 | D57: =D48*'College Inputs'!$B$63*'College Inputs'!$B$64*'College Inputs'!$B$17*D49*(1-D53)/100000 -> 1.9948738 | E57: =E48*'College Inputs'!$B$63*'College Inputs'!$B$64*'College Inputs'!$B$17*E49*(1-E53)/100000 -> 3.0562373 | F57: =F48*'College Inputs'!$B$63*'College Inputs'!$B$64*'College Inputs'!$B$17*F49*(1-F53)/100000 -> 4.0346301
A58: Setup fees | B58: =B46*'College Inputs'!$B$65*'College Inputs'!$B$33/100000 -> 1.25 | C58: =C46*'College Inputs'!$B$65*'College Inputs'!$B$33/100000 -> 2.5 | D58: =D46*'College Inputs'!$B$65*'College Inputs'!$B$33/100000 -> 3.75 | E58: =E46*'College Inputs'!$B$65*'College Inputs'!$B$33/100000 -> 3.75 | F58: =F46*'College Inputs'!$B$65*'College Inputs'!$B$33/100000 -> 3.75
A59: TOTAL REVENUE | B59: =SUM(B54:B58) -> 15.506 | C59: =SUM(C54:C58) -> 50.865096 | D59: =SUM(D54:D58) -> 109.07933 | E59: =SUM(E54:E58) -> 165.11933 | F59: =SUM(F54:F58) -> 216.77847
A60: Licence running cost | B60: =B48*'College Inputs'!$B$58*SUMPRODUCT('College Inputs'!$B$68:$B$71,'College Inputs'!$J$6:$J$9)/100000 -> 4.0125 | C60: =C48*'College Inputs'!$B$58*SUMPRODUCT('College Inputs'!$B$68:$B$71,'College Inputs'!$J$6:$J$9)/100000 -> 11.63625 | D60: =D48*'College Inputs'!$B$58*SUMPRODUCT('College Inputs'!$B$68:$B$71,'College Inputs'!$J$6:$J$9)/100000 -> 22.06875 | E60: =E48*'College Inputs'!$B$58*SUMPRODUCT('College Inputs'!$B$68:$B$71,'College Inputs'!$J$6:$J$9)/100000 -> 30.89625 | F60: =F48*'College Inputs'!$B$58*SUMPRODUCT('College Inputs'!$B$68:$B$71,'College Inputs'!$J$6:$J$9)/100000 -> 38.11875
A61: Add-on running cost | B61: =B48*('College Inputs'!$B$61*SUMPRODUCT('College Inputs'!$B$75:$B$79,'College Inputs'!$F$22:$F$26)+'College Inputs'!$B$62*'College Inputs'!$C$32+'College Inputs'!$B$63*'College Inputs'!$B$64*'College Inputs'!$C$17)/100000 -> 0.5976 | C61: =C48*('College Inputs'!$B$61*SUMPRODUCT('College Inputs'!$B$75:$B$79,'College Inputs'!$F$22:$F$26)+'College Inputs'!$B$62*'College Inputs'!$C$32+'College Inputs'!$B$63*'College Inputs'!$B$64*'College Inputs'!$C$17)/100000 -> 1.73304 | D61: =D48*('College Inputs'!$B$61*SUMPRODUCT('College Inputs'!$B$75:$B$79,'College Inputs'!$F$22:$F$26)+'College Inputs'!$B$62*'College Inputs'!$C$32+'College Inputs'!$B$63*'College Inputs'!$B$64*'College Inputs'!$C$17)/100000 -> 3.2868 | E61: =E48*('College Inputs'!$B$61*SUMPRODUCT('College Inputs'!$B$75:$B$79,'College Inputs'!$F$22:$F$26)+'College Inputs'!$B$62*'College Inputs'!$C$32+'College Inputs'!$B$63*'College Inputs'!$B$64*'College Inputs'!$C$17)/100000 -> 4.60152 | F61: =F48*('College Inputs'!$B$61*SUMPRODUCT('College Inputs'!$B$75:$B$79,'College Inputs'!$F$22:$F$26)+'College Inputs'!$B$62*'College Inputs'!$C$32+'College Inputs'!$B$63*'College Inputs'!$B$64*'College Inputs'!$C$17)/100000 -> 5.6772
A62: Onboarding travel (new colleges) | B62: =B46*'College Inputs'!$C$33/100000 -> 1.5 | C62: =C46*'College Inputs'!$C$33/100000 -> 3 | D62: =D46*'College Inputs'!$C$33/100000 -> 4.5 | E62: =E46*'College Inputs'!$C$33/100000 -> 4.5 | F62: =F46*'College Inputs'!$C$33/100000 -> 4.5
A63: Retraining visits (renewing colleges) | B63: =B47*'College Inputs'!$C$34/100000 -> 0 | C63: =C47*'College Inputs'!$C$34/100000 -> 0.45 | D63: =D47*'College Inputs'!$C$34/100000 -> 1.25 | E63: =E47*'College Inputs'!$C$34/100000 -> 2.35 | F63: =F47*'College Inputs'!$C$34/100000 -> 3.25
A64: GROSS PROFIT | B64: =B59-SUM(B60:B63) -> 9.3959 | C64: =C59-SUM(C60:C63) -> 34.045806 | D64: =D59-SUM(D60:D63) -> 77.973785 | E64: =E59-SUM(E60:E63) -> 122.77156 | F64: =F59-SUM(F60:F63) -> 165.23252
A65: Gross margin | B65: =IF(B59=0,0,B64/B59) -> 0.60595253 | C65: =IF(C59=0,0,C64/C59) -> 0.66933533 | D65: =IF(D59=0,0,D64/D59) -> 0.71483554 | E65: =IF(E59=0,0,E64/E59) -> 0.74353233 | F65: =IF(F59=0,0,F64/F59) -> 0.76221831
A66: Other fixed expenses | B66: ='College Inputs'!$B$55/100000 -> 3 | C66: ='College Inputs'!$B$55/100000 -> 3 | D66: ='College Inputs'!$B$55/100000 -> 3 | E66: ='College Inputs'!$B$55/100000 -> 3 | F66: ='College Inputs'!$B$55/100000 -> 3
A67: NET PROFIT (before tax) | B67: =B64-B66 -> 6.3959 | C67: =C64-C66 -> 31.045806 | D67: =D64-D66 -> 74.973785 | E67: =E64-E66 -> 119.77156 | F67: =F64-F66 -> 162.23252
A68: Cumulative net profit | B68: =B67 -> 6.3959 | C68: =B68+C67 -> 37.441706 | D68: =C68+D67 -> 112.41549 | E68: =D68+E67 -> 232.18705 | F68: =E68+F67 -> 394.41957
A69: Position after recovering the Rs 10 lakh investment | B69: =B68-'College Inputs'!$B$54/100000 -> -3.6041 | C69: =C68-'College Inputs'!$B$54/100000 -> 27.441706 | D69: =D68-'College Inputs'!$B$54/100000 -> 102.41549 | E69: =E68-'College Inputs'!$B$54/100000 -> 222.18705 | F69: =F68-'College Inputs'!$B$54/100000 -> 384.41957
A72: OPTIMISTIC SCENARIO
A73: Rs lakh unless stated | B73: Year 1 | C73: Year 2 | D73: Year 3 | E73: Year 4 | F73: Year 5
A74: New colleges signed | B74: ='College Inputs'!B88 -> 20 | C74: ='College Inputs'!C88 -> 35 | D74: ='College Inputs'!D88 -> 50 | E74: ='College Inputs'!E88 -> 50 | F74: ='College Inputs'!F88 -> 50
A75: Renewing colleges | B75: =0 -> 0 | C75: =ROUND(B76*'College Inputs'!$B$56,0) -> 17 | D75: =ROUND(C76*'College Inputs'!$B$56,0) -> 44 | E75: =ROUND(D76*'College Inputs'!$B$56,0) -> 80 | F75: =ROUND(E76*'College Inputs'!$B$56,0) -> 111
A76: Active colleges | B76: =MIN('College Inputs'!$B$57,B74+B75) -> 20 | C76: =MIN('College Inputs'!$B$57,C74+C75) -> 52 | D76: =MIN('College Inputs'!$B$57,D74+D75) -> 94 | E76: =MIN('College Inputs'!$B$57,E74+E75) -> 130 | F76: =MIN('College Inputs'!$B$57,F74+F75) -> 161
A77: Price index (annual increase) | B77: =1 -> 1 | C77: =B77*(1+'College Inputs'!$B$47) -> 1.07 | D77: =C77*(1+'College Inputs'!$B$47) -> 1.1449 | E77: =D77*(1+'College Inputs'!$B$47) -> 1.225043 | F77: =E77*(1+'College Inputs'!$B$47) -> 1.310796
A78: Average licence fees per college (Rs, after volume discount) | B78: ='College Inputs'!$B$58*SUMPRODUCT('College Inputs'!$B$68:$B$71,'College Inputs'!$H$6:$H$9)*(1-'College Inputs'!$B$59)*B77 -> 147400 | C78: ='College Inputs'!$B$58*SUMPRODUCT('College Inputs'!$B$68:$B$71,'College Inputs'!$H$6:$H$9)*(1-'College Inputs'!$B$59)*C77 -> 157718 | D78: ='College Inputs'!$B$58*SUMPRODUCT('College Inputs'!$B$68:$B$71,'College Inputs'!$H$6:$H$9)*(1-'College Inputs'!$B$59)*D77 -> 168758.26 | E78: ='College Inputs'!$B$58*SUMPRODUCT('College Inputs'!$B$68:$B$71,'College Inputs'!$H$6:$H$9)*(1-'College Inputs'!$B$59)*E77 -> 180571.34 | F78: ='College Inputs'!$B$58*SUMPRODUCT('College Inputs'!$B$68:$B$71,'College Inputs'!$H$6:$H$9)*(1-'College Inputs'!$B$59)*F77 -> 193211.33
A79: Average extra-user charges per college (Rs) | B79: ='College Inputs'!$B$60*B77 -> 9000 | C79: ='College Inputs'!$B$60*C77 -> 9630 | D79: ='College Inputs'!$B$60*D77 -> 10304.1 | E79: ='College Inputs'!$B$60*E77 -> 11025.387 | F79: ='College Inputs'!$B$60*F77 -> 11797.164
A80: Average Intern Programme price (Rs) | B80: =SUMPRODUCT('College Inputs'!$B$75:$B$79,'College Inputs'!$D$22:$D$26)*B77 -> 45200 | C80: =SUMPRODUCT('College Inputs'!$B$75:$B$79,'College Inputs'!$D$22:$D$26)*C77 -> 48364 | D80: =SUMPRODUCT('College Inputs'!$B$75:$B$79,'College Inputs'!$D$22:$D$26)*D77 -> 51749.48 | E80: =SUMPRODUCT('College Inputs'!$B$75:$B$79,'College Inputs'!$D$22:$D$26)*E77 -> 55371.944 | F80: =SUMPRODUCT('College Inputs'!$B$75:$B$79,'College Inputs'!$D$22:$D$26)*F77 -> 59247.98
A81: Average commercial discount | B81: ='College Inputs'!B83 -> 0.25 | C81: ='College Inputs'!C83 -> 0.18 | D81: ='College Inputs'!D83 -> 0.12 | E81: ='College Inputs'!E83 -> 0.1 | F81: ='College Inputs'!F83 -> 0.1
A82: Licence + extra-user revenue | B82: =B76*(B78+B79)*(1-B81)/100000 -> 23.46 | C82: =C76*(C78+C79)*(1-C81)/100000 -> 71.357187 | D82: =D76*(D78+D79)*(1-D81)/100000 -> 148.12038 | E82: =E76*(E78+E79)*(1-E81)/100000 -> 224.16817 | F82: =F76*(F78+F79)*(1-F81)/100000 -> 297.05731
A83: Intern Programme revenue | B83: =B76*'College Inputs'!$B$61*B80*(1-B81)/100000 -> 2.712 | C83: =C76*'College Inputs'!$B$61*C80*(1-C81)/100000 -> 8.2489638 | D83: =D76*'College Inputs'!$B$61*D80*(1-D81)/100000 -> 17.122868 | E83: =E76*'College Inputs'!$B$61*E80*(1-E81)/100000 -> 25.91407 | F83: =F76*'College Inputs'!$B$61*F80*(1-F81)/100000 -> 34.340129
A84: Research Module revenue | B84: =B76*'College Inputs'!$B$62*'College Inputs'!$B$32*B77*(1-B81)/100000 -> 1.8 | C84: =C76*'College Inputs'!$B$62*'College Inputs'!$B$32*C77*(1-C81)/100000 -> 5.474976 | D84: =D76*'College Inputs'!$B$62*'College Inputs'!$B$32*D77*(1-D81)/100000 -> 11.364735 | E84: =E76*'College Inputs'!$B$62*'College Inputs'!$B$32*E77*(1-E81)/100000 -> 17.199604 | F84: =F76*'College Inputs'!$B$62*'College Inputs'!$B$32*F77*(1-F81)/100000 -> 22.792121
A85: Fellowship revenue | B85: =B76*'College Inputs'!$B$63*'College Inputs'!$B$64*'College Inputs'!$B$17*B77*(1-B81)/100000 -> 0.54 | C85: =C76*'College Inputs'!$B$63*'College Inputs'!$B$64*'College Inputs'!$B$17*C77*(1-C81)/100000 -> 1.6424928 | D85: =D76*'College Inputs'!$B$63*'College Inputs'!$B$64*'College Inputs'!$B$17*D77*(1-D81)/100000 -> 3.4094206 | E85: =E76*'College Inputs'!$B$63*'College Inputs'!$B$64*'College Inputs'!$B$17*E77*(1-E81)/100000 -> 5.1598811 | F85: =F76*'College Inputs'!$B$63*'College Inputs'!$B$64*'College Inputs'!$B$17*F77*(1-F81)/100000 -> 6.8376363
A86: Setup fees | B86: =B74*'College Inputs'!$B$65*'College Inputs'!$B$33/100000 -> 2.5 | C86: =C74*'College Inputs'!$B$65*'College Inputs'!$B$33/100000 -> 4.375 | D86: =D74*'College Inputs'!$B$65*'College Inputs'!$B$33/100000 -> 6.25 | E86: =E74*'College Inputs'!$B$65*'College Inputs'!$B$33/100000 -> 6.25 | F86: =F74*'College Inputs'!$B$65*'College Inputs'!$B$33/100000 -> 6.25
A87: TOTAL REVENUE | B87: =SUM(B82:B86) -> 31.012 | C87: =SUM(C82:C86) -> 91.09862 | D87: =SUM(D82:D86) -> 186.26741 | E87: =SUM(E82:E86) -> 278.69172 | F87: =SUM(F82:F86) -> 367.2772
A88: Licence running cost | B88: =B76*'College Inputs'!$B$58*SUMPRODUCT('College Inputs'!$B$68:$B$71,'College Inputs'!$J$6:$J$9)/100000 -> 8.025 | C88: =C76*'College Inputs'!$B$58*SUMPRODUCT('College Inputs'!$B$68:$B$71,'College Inputs'!$J$6:$J$9)/100000 -> 20.865 | D88: =D76*'College Inputs'!$B$58*SUMPRODUCT('College Inputs'!$B$68:$B$71,'College Inputs'!$J$6:$J$9)/100000 -> 37.7175 | E88: =E76*'College Inputs'!$B$58*SUMPRODUCT('College Inputs'!$B$68:$B$71,'College Inputs'!$J$6:$J$9)/100000 -> 52.1625 | F88: =F76*'College Inputs'!$B$58*SUMPRODUCT('College Inputs'!$B$68:$B$71,'College Inputs'!$J$6:$J$9)/100000 -> 64.60125
A89: Add-on running cost | B89: =B76*('College Inputs'!$B$61*SUMPRODUCT('College Inputs'!$B$75:$B$79,'College Inputs'!$F$22:$F$26)+'College Inputs'!$B$62*'College Inputs'!$C$32+'College Inputs'!$B$63*'College Inputs'!$B$64*'College Inputs'!$C$17)/100000 -> 1.1952 | C89: =C76*('College Inputs'!$B$61*SUMPRODUCT('College Inputs'!$B$75:$B$79,'College Inputs'!$F$22:$F$26)+'College Inputs'!$B$62*'College Inputs'!$C$32+'College Inputs'!$B$63*'College Inputs'!$B$64*'College Inputs'!$C$17)/100000 -> 3.10752 | D89: =D76*('College Inputs'!$B$61*SUMPRODUCT('College Inputs'!$B$75:$B$79,'College Inputs'!$F$22:$F$26)+'College Inputs'!$B$62*'College Inputs'!$C$32+'College Inputs'!$B$63*'College Inputs'!$B$64*'College Inputs'!$C$17)/100000 -> 5.61744 | E89: =E76*('College Inputs'!$B$61*SUMPRODUCT('College Inputs'!$B$75:$B$79,'College Inputs'!$F$22:$F$26)+'College Inputs'!$B$62*'College Inputs'!$C$32+'College Inputs'!$B$63*'College Inputs'!$B$64*'College Inputs'!$C$17)/100000 -> 7.7688 | F89: =F76*('College Inputs'!$B$61*SUMPRODUCT('College Inputs'!$B$75:$B$79,'College Inputs'!$F$22:$F$26)+'College Inputs'!$B$62*'College Inputs'!$C$32+'College Inputs'!$B$63*'College Inputs'!$B$64*'College Inputs'!$C$17)/100000 -> 9.62136
A90: Onboarding travel (new colleges) | B90: =B74*'College Inputs'!$C$33/100000 -> 3 | C90: =C74*'College Inputs'!$C$33/100000 -> 5.25 | D90: =D74*'College Inputs'!$C$33/100000 -> 7.5 | E90: =E74*'College Inputs'!$C$33/100000 -> 7.5 | F90: =F74*'College Inputs'!$C$33/100000 -> 7.5
A91: Retraining visits (renewing colleges) | B91: =B75*'College Inputs'!$C$34/100000 -> 0 | C91: =C75*'College Inputs'!$C$34/100000 -> 0.85 | D91: =D75*'College Inputs'!$C$34/100000 -> 2.2 | E91: =E75*'College Inputs'!$C$34/100000 -> 4 | F91: =F75*'College Inputs'!$C$34/100000 -> 5.55
A92: GROSS PROFIT | B92: =B87-SUM(B88:B91) -> 18.7918 | C92: =C87-SUM(C88:C91) -> 61.0261 | D92: =D87-SUM(D88:D91) -> 133.23247 | E92: =E87-SUM(E88:E91) -> 207.26042 | F92: =F87-SUM(F88:F91) -> 280.00459
A93: Gross margin | B93: =IF(B87=0,0,B92/B87) -> 0.60595253 | C93: =IF(C87=0,0,C92/C87) -> 0.6698905 | D93: =IF(D87=0,0,D92/D87) -> 0.71527526 | E93: =IF(E87=0,0,E92/E87) -> 0.74369063 | F93: =IF(F87=0,0,F92/F87) -> 0.76237945
A94: Other fixed expenses | B94: ='College Inputs'!$B$55/100000 -> 3 | C94: ='College Inputs'!$B$55/100000 -> 3 | D94: ='College Inputs'!$B$55/100000 -> 3 | E94: ='College Inputs'!$B$55/100000 -> 3 | F94: ='College Inputs'!$B$55/100000 -> 3
A95: NET PROFIT (before tax) | B95: =B92-B94 -> 15.7918 | C95: =C92-C94 -> 58.0261 | D95: =D92-D94 -> 130.23247 | E95: =E92-E94 -> 204.26042 | F95: =F92-F94 -> 277.00459
A96: Cumulative net profit | B96: =B95 -> 15.7918 | C96: =B96+C95 -> 73.8179 | D96: =C96+D95 -> 204.05037 | E96: =D96+E95 -> 408.31079 | F96: =E96+F95 -> 685.31538
A97: Position after recovering the Rs 10 lakh investment | B97: =B96-'College Inputs'!$B$54/100000 -> 5.7918 | C97: =C96-'College Inputs'!$B$54/100000 -> 63.8179 | D97: =D96-'College Inputs'!$B$54/100000 -> 194.05037 | E97: =E96-'College Inputs'!$B$54/100000 -> 398.31079 | F97: =F96-'College Inputs'!$B$54/100000 -> 675.31538

Sheet College Inputs
A1: Implanr — College pricing inputs (one source for the rate card, quote and model)
A2: Blue text = a number you can change. Yellow fill = an assumption Claude made that you should check. Black = formula. Prices are per year, in rupees, excluding 18% GST.
A4: A. LICENCE TIERS — one licence per department, Centralised Implant Clinic or Unit, sized by PG students on roll (all 3 years)
A5: Tier | B5: MDS seats per year | C5: PG students from | D5: PG students to (all 3 yrs) | E5: Supervisors included | F5: Implant in-charges included | G5: College admins included | H5: Annual price (Rs, excl GST) | I5: Your cost (Rs / month) | J5: Your cost (Rs / year) | K5: Gross margin | L5: Note
A6: Essential 9 | B6: 3 | C6: 1 | D6: 9 | E6: 3 | F6: 1 | G6: 1 | H6: 50000 | I6: 1000 | J6: =I6*12 -> 12000 | K6: =IF(H6=0,0,(H6-J6)/H6) -> 0.76 | L6: Seats, students and staff numbers: user-stated. Price: Claude's recommendation.
A7: Standard 12 | B7: 4 | C7: 10 | D7: 12 | E7: 4 | F7: 2 | G7: 1 | H7: 60000 | I7: 1250 | J7: =I7*12 -> 15000 | K7: =IF(H7=0,0,(H7-J7)/H7) -> 0.75
A8: Advanced 18 | B8: 6 | C8: 13 | D8: 18 | E8: 5 | F8: 3 | G8: 2 | H8: 80000 | I8: 1500 | J8: =I8*12 -> 18000 | K8: =IF(H8=0,0,(H8-J8)/H8) -> 0.775
A9: Premier 24 | B9: 8 | C9: 19 | D9: 24 | E9: 6 | F9: 4 | G9: 2 | H9: 100000 | I9: 2000 | J9: =I9*12 -> 24000 | K9: =IF(H9=0,0,(H9-J9)/H9) -> 0.76
A11: B. EXTRA USERS, EXTRA STUDENTS AND FELLOWS (per person per year)
A12: Item | B12: Price (Rs / yr) | C12: Your cost (Rs / yr) | D12: Note
A13: Extra supervisor / guide | B13: 3000 | C13: 300 | D13: Same as your earlier Rs 250 a month faculty add-on.
A14: Extra implant in-charge | B14: 4000 | C14: 300 | D14: In-charges see the unit dashboard and manage its users.
A15: Extra college admin | B15: 5000 | C15: 300 | D15: Same as your earlier Rs 400 a month admin add-on, rounded.
A16: Extra PG student above 24 on one licence | B16: 4000 | C16: 600 | D16: Only for a Premier 24 licence holding more than 24 PGs, e.g. a large Centralised Implant Clinic.
A17: Fellow (Fellowship in Implantology) | B17: 6000 | C17: 1200 | D17: Counted separately from MDS students (user-stated).
A18: Management viewer (Dean, Principal, HOD) — read-only | B18: 0 | C18: 0 | D18: Free, up to 3 per college. The people who sign the cheque should see the dashboard.
A20: C. INTERN IMPLANT PROGRAMME — interns who place implants (observing and assisting stay free)
A21: Tier | B21: Interns from | C21: Interns to | D21: Annual price (Rs) | E21: Price per intern | F21: Your cost (Rs / yr) | G21: Note
A22: Interns 20 | B22: 1 | C22: 20 | D22: 15000 | E22: =D22/C22 -> 750 | F22: =C22*$B$28 -> 2400 | G22: Interns place 2–5 implants each (user-stated), so 20 interns = 40–100 extra cases a year.
A23: Interns 40 | B23: 21 | C23: 40 | D23: 28000 | E23: =D23/C23 -> 700 | F23: =C23*$B$28 -> 4800
A24: Interns 60 | B24: 41 | C24: 60 | D24: 40000 | E24: =D24/C24 -> 666.66667 | F24: =C24*$B$28 -> 7200
A25: Interns 80 | B25: 61 | C25: 80 | D25: 50000 | E25: =D25/C25 -> 625 | F25: =C25*$B$28 -> 9600
A26: Interns 100 | B26: 81 | C26: 100 | D26: 60000 | E26: =D26/C26 -> 600 | F26: =C26*$B$28 -> 12000
A27: Above 100 interns — per extra intern | B27: 600 | C27: Added to the Interns 100 price.
A28: Your cost per intern per year | B28: 120 | C28: Assumption: storage and AI for 2–5 extra cases per intern.
A30: D. OTHER ADD-ONS AND ONE-TIME FEES
A31: Item | B31: Price (Rs / yr) | C31: Your cost (Rs / yr) | D31: Note
A32: Research Module (per college) | B32: 40000 | C32: 6000 | D32: Paid add-on (your decision of 14 Oct 2026).
A33: Onboarding & setup fee (one-time, per new college) | B33: 25000 | C33: 15000 | D33: Covers your in-person launch visit; cost = your travel. Waived on 3-year contracts.
A34: Annual retraining for the new PG batch (per college) | B34: 0 | C34: 5000 | D34: Included in the licence (in person + remote, user-stated). Cost = your travel and time.
A35: Extra image storage above fair use (per 100 GB) | B35: 2500 | C35: 600 | D35: See fair-use limit in section E.
A37: E. DISCOUNTS AND COMMERCIAL TERMS
A38: Term | B38: Value | C38: Note
A39: Volume discount — 2 licences | B39: 0.1 | C39: On licence fees, e.g. Prosthodontics + Periodontology.
A40: Volume discount — 3 or more licences | B40: 0.15 | C40: On licence fees, e.g. all three departments, or a central clinic plus units.
A41: University / group discount | B41: 0.15 | C41: Replaces the volume discount when higher (they do not stack).
A42: Founding-institution discount | B42: 0.25 | C42: Price locked for 3 years, in return for a case study and reference visits.
A43: Founding slots (colleges) | B43: 20 | C43: Close the offer after this many colleges.
A44: Government college discount | B44: 0.2 | C44: Government colleges buy through GeM / tender.
A45: 3-year prepaid discount | B45: 0.1 | C45: Paid upfront for 3 years; setup fee waived.
A46: Maximum combined commercial discount | B46: 0.3 | C46: Cap on founding + government + 3-year + negotiated. Volume / group discount is applied first, separately.
A47: Annual price increase on renewal | B47: 0.07 | C47: Not applied to founding colleges during their 3 locked years.
A48: GST | B48: 0.18 | C48: Charged on top of every invoice.
A49: Minimum ongoing gross margin on any quote | B49: 0.6 | C49: The quote warns you below this.
A50: Fair-use image storage per licence (GB) | B50: 250 | C50: Assumption. Generous for 50–150 cases a year with CBCT; protects you from one heavy user.
A52: F. REVENUE MODEL ASSUMPTIONS
A53: Assumption | B53: Value | C53: Source
A54: Initial investment to recover (Rs) | B54: 1000000 | C54: User-stated.
A55: Other fixed expenses per year (Rs) | B55: 300000 | C55: Assumption: base servers, app stores, development, marketing, sales travel, legal. Replace with your figure.
A56: Renewal rate | B56: 0.85 | C56: Assumption.
A57: Dental colleges with MDS seats (market ceiling) | B57: 289 | C57: User-stated.
A58: Average licences per college | B58: 2.5 | C58: Assumption: most take all 3 departments; some take 1, or a single Centralised Implant Clinic.
A59: Average volume discount on licence fees | B59: 0.12 | C59: Assumption, consistent with 2.5 licences a college.
A60: Average extra-user charges per college (Rs / yr) | B60: 9000 | C60: Assumption: about 3 extra supervisors.
A61: Share of colleges taking the Intern Implant Programme | B61: 0.4 | C61: Assumption: colleges that let interns place implants.
A62: Share taking the Research Module | B62: 0.3 | C62: Assumption.
A63: Share with an implant fellowship | B63: 0.15 | C63: Assumption.
A64: Fellows per such college | B64: 4 | C64: Assumption.
A65: Share of new colleges paying the setup fee | B65: 0.5 | C65: Assumption: the rest sign 3-year contracts.
A67: Mix of licences by tier | B67: Share | C67: Note
A68: =A6 -> Essential 9 | B68: 0.3 | C68: Assumption.
A69: =A7 -> Standard 12 | B69: 0.35
A70: =A8 -> Advanced 18 | B70: 0.2
A71: =A9 -> Premier 24 | B71: 0.15
A72: Total (must be 100%) | B72: =SUM(B68:B71) -> 1 | C72: =IF(ROUND(B72,4)=1,"OK","Does not add up to 100% — fix the shares above") -> OK
A74: Mix of Intern Programme tiers | B74: Share | C74: Note
A75: =A22 -> Interns 20 | B75: 0.1 | C75: Assumption.
A76: =A23 -> Interns 40 | B76: 0.15
A77: =A24 -> Interns 60 | B77: 0.2
A78: =A25 -> Interns 80 | B78: 0.15
A79: =A26 -> Interns 100 | B79: 0.4
A80: Total (must be 100%) | B80: =SUM(B75:B79) -> 1 | C80: =IF(ROUND(B80,4)=1,"OK","Does not add up to 100% — fix the shares above") -> OK
A82: Average commercial discount, by year | B82: Year 1 | C82: Year 2 | D82: Year 3 | E82: Year 4 | F82: Year 5
A83: Average across all active colleges | B83: 0.25 | C83: 0.18 | D83: 0.12 | E83: 0.1 | F83: 0.1 | G83: Assumption: year 1 is mostly founding colleges.
A85: New colleges signed per year | B85: Year 1 | C85: Year 2 | D85: Year 3 | E85: Year 4 | F85: Year 5
A86: Conservative | B86: 5 | C86: 10 | D86: 15 | E86: 15 | F86: 15 | G86: Assumption. Replace with your own targets.
A87: Base | B87: 10 | C87: 20 | D87: 30 | E87: 30 | F87: 30
A88: Optimistic | B88: 20 | C88: 35 | D88: 50 | E88: 50 | F88: 50

Sheet College Plans (old v1)
A1: Implanr — Dental College Subscription Plans
A2: Institution-wide access. Priced per college, not per student — unlimited case learning for every resident.
A3: DEPARTMENT/UNIT | C3: COLLEGE | E3: COLLEGE | G3: University | I3: Need a custom quote? WhatsApp our team
A4: Single implant dept (Oral Surgery / Prostho/ Periodontology) | C4: Postgraduate students all implant depts | E4: Postgraduat and Undergraduate students | G4: Multiple dental colleges under one university
A5: Up to 25 students 5 faculty + 1 admin | C5: Up to 50 students 12 faculty + 2 admin | E5: Up to 125 students 20 faculty + 2 admin | G5: Unlimited users Full data export
A6: Rs 8,000/mo | C6: Rs 12,000/mo | E6: Rs 25,000/mo | G6: Custom
A7: Rs 70,000/yr (save Rs 16,000) | C7: Rs 1,20,000/yr (save Rs 24,000) | E7: Rs 2,50,000/yr (save Rs 50,000) | G7: Custom
A8: Just Rs 320/student/month | C8: Just Rs 240/student/month | E8: Just Rs 200/student/month
A10: USER ROLES — WHO GETS ACCESS AND WHAT THEY CAN DO
A11: User Role | B11: What They Can Do | C11: Dept | D11: College | E11: University | F11: Research | G11: Count (Dept) | H11: Count (College) | I11: Count (Univ)
A12: Student / PG Student/ Fellow | B12: Full case creation, CBCT upload, treatment documentation, AI notes, report generation. Their own patient cases. | C12: Yes | D12: Yes | E12: Yes | F12: Yes | G12: Up to 25 | H12: Up to 75 or upto 100 | I12: Up to 200
A13: Supervisor/Guide | B13: Supervise student cases, approve plans, add reviewer notes, run department case reports. | C13: Yes | D13: Yes | E13: Yes | F13: Yes | G13: Up to 5 | H13: Up to 14 or upto 22 | I13: Up to 75
A14: Department/ Unit In-Charge | B14: Full department view, analytics dashboard, faculty management, academic data export, department audit trail | C14: Yes | D14: Yes | E14: Yes | F14: Yes | G14: 1 | H14: Up to 6 | I14: Unlimited
A15: College Admin | B15: Institution-level access, all accounts, college-wide reports, compliance exports, college level audit report | C15: Yes | D15: Yes | E15: Yes | F15: Yes | G15: — | H15: 2 | I15: 2
A17: ADD-ON SEATS — Extra Student: Rs 100/mo | Extra Faculty: Rs 250/mo | Extra Admin: Rs 400/mo
